birdysis/__init__.py
birdysis/collect_data/__init__.py
birdysis/collect_data/scrape.py
birdysis/download/__init__.py
birdysis/download/cleanmedia.py
birdysis/download/functions.py
birdysis/download/tweepydl.py
src/__init__.py
src/__main__.py
src/cleanmedia.py
src/functions.py
src/scrape.py
src/tweepydl.py
birdysis-0.1.4.dist-info/LICENSE
birdysis-0.1.4.dist-info/METADATA
birdysis-0.1.4.dist-info/WHEEL
birdysis-0.1.4.dist-info/entry_points.txt
birdysis-0.1.4.dist-info/top_level.txt
birdysis-0.1.4.dist-info/RECORD
