Metadata-Version: 2.1
Name: birdysis
Version: 0.1.4
Summary: Retrieves and downloads liked tweets on Twitter.
Home-page: https://github.com/sweeneyngo/birdysis
Author: Sweeney Ngo
Author-email: sweeneyngo@gmail.com
License: LICENSE
Platform: UNKNOWN
Classifier: Programming Language :: Python :: 3
Classifier: License :: OSI Approved :: MIT License
Classifier: Operating System :: OS Independent
Requires-Python: >=3.6
Requires-Dist: tweepy
Requires-Dist: selenium
Requires-Dist: cryptography
